cheapcone/__init__.py
cheapcone/client.py
cheapcone/json.py
cheapcone/proxy.py
cheapcone/schemas.py
cheapcone/typedefs.py
cheapcone-0.1.10.dist-info/METADATA
cheapcone-0.1.10.dist-info/WHEEL
cheapcone-0.1.10.dist-info/RECORD
